malojalib/__init__.py
malojalib/__pkginfo__.py
maloja_lib-1.0.0.dist-info/LICENSE
maloja_lib-1.0.0.dist-info/METADATA
maloja_lib-1.0.0.dist-info/WHEEL
maloja_lib-1.0.0.dist-info/entry_points.txt
maloja_lib-1.0.0.dist-info/top_level.txt
maloja_lib-1.0.0.dist-info/RECORD
