Metadata-Version: 2.1
Name: maloja-lib
Version: 1.0.0
Summary: Utilities to interact with Maloja servers
Home-page: https://github.com/krateng/maloja
Author: Johannes Krattenmacher
Author-email: maloja@dev.krateng.ch
License: GPLv3
Platform: UNKNOWN
Classifier: Programming Language :: Python :: 3
Classifier: License :: OSI Approved :: GNU General Public License v3 (GPLv3)
Classifier: Operating System :: OS Independent
Requires-Python: >=3.6
Requires-Dist: requests
